fast_logging/__init__.py
fast_logging/console.py
fast_logging/fastlogging.py
fast_logging/network.py
fast_logging/optimize.py
fast_logging-1.0.2.dist-info/LICENSE.txt
fast_logging-1.0.2.dist-info/METADATA
fast_logging-1.0.2.dist-info/WHEEL
fast_logging-1.0.2.dist-info/top_level.txt
fast_logging-1.0.2.dist-info/RECORD
