Metadata-Version: 2.1
Name: fast-logging
Version: 1.0.2
Summary: A faster replacement of the standard logging module.
Home-page: https://github.com/RailYakup/fastlogging
Author: Martin Bammer
Author-email: mrbm74@gmail.com
License: MIT
Download-URL: https://github.com/RailYakup/fastlogging/releases/download/1.0.2/fastlogging-1.0.2.tar.gz
Keywords: fast logging
Platform: UNKNOWN
Classifier: Development Status :: 4 - Beta
Classifier: Intended Audience :: Developers
Classifier: Topic :: Software Development :: Build Tools
Classifier: License :: OSI Approved :: MIT License
Classifier: Operating System :: OS Independent
Classifier: Programming Language :: Python :: 2
Classifier: Programming Language :: Python :: 2.7
Classifier: Programming Language :: Python :: 3
Classifier: Programming Language :: Python :: 3.4
Classifier: Programming Language :: Python :: 3.5
Classifier: Programming Language :: Python :: 3.6
Classifier: Programming Language :: Python :: 3.7
Classifier: Programming Language :: Python :: 3.8
